{
    "android_gradle_plugin_version": "2.1.3",
    "apk_path": "E:\\MyWorkSpace\\DoingDaily\\app\\build\\outputs\\apk\\app-debug.apk",
    "auto_dependency": true,
    "build_cache_dir": "E:\\MyWorkSpace\\DoingDaily\\app\\build\\freeline",
    "build_directory": "E:\\MyWorkSpace\\DoingDaily\\app\\build",
    "build_script": "gradlew.bat :app:assembleDebug",
    "build_script_work_directory": "",
    "build_tools_directory": "D:\\AndroidDevTools\\sdk\\build-tools\\24.0.2",
    "build_tools_version": "24.0.2",
    "compile_sdk_directory": "D:\\AndroidDevTools\\sdk\\platforms\\android-23",
    "compile_sdk_version": "android-23",
    "databinding": [
        
    ],
    "databinding_modules": [
        
    ],
    "debug_package": "com.ganxin.doingdaily",
    "exclude_dep_res_paths": [
        
    ],
    "extra_dep_res_paths": [
        
    ],
    "freeline_cache_dir": "E:\\MyWorkSpace\\DoingDaily",
    "freeline_gradle_plugin_version": "0.8.3",
    "java_home": "D:\\AndroidDevTools\\Java\\jdk1.8.0_65",
    "launcher": "com.ganxin.doingdaily.module.loading.LoadingActivity",
    "main_assets_directory": [
        "E:\\MyWorkSpace\\DoingDaily\\app\\src\\debug\\assets",
        "E:\\MyWorkSpace\\DoingDaily\\app\\src\\main\\assets"
    ],
    "main_jniLibs_directory": [
        "E:\\MyWorkSpace\\DoingDaily\\app\\src\\debug\\jniLibs",
        "E:\\MyWorkSpace\\DoingDaily\\app\\src\\main\\jniLibs"
    ],
    "main_jni_directory": [
        "E:\\MyWorkSpace\\DoingDaily\\app\\src\\debug\\jni",
        "E:\\MyWorkSpace\\DoingDaily\\app\\src\\main\\jni"
    ],
    "main_manifest_path": "E:\\MyWorkSpace\\DoingDaily\\app\\src\\main\\AndroidManifest.xml",
    "main_project_dir": "app",
    "main_project_name": "app",
    "main_r_path": "E:\\MyWorkSpace\\DoingDaily\\app\\build\\generated\\source\\r\\debug\\R.java",
    "main_res_directory": [
        "E:\\MyWorkSpace\\DoingDaily\\app\\src\\debug\\res",
        "E:\\MyWorkSpace\\DoingDaily\\app\\src\\main\\res"
    ],
    "main_src_directory": [
        "E:\\MyWorkSpace\\DoingDaily\\app\\src\\debug\\java",
        "E:\\MyWorkSpace\\DoingDaily\\app\\src\\main\\java"
    ],
    "module_dependencies": {
        "app": [
            
        ]
    },
    "modules": [
        {
            "name": "app",
            "path": "E:\\MyWorkSpace\\DoingDaily\\app"
        }
    ],
    "package": "com.ganxin.doingdaily",
    "product_flavor": "",
    "project_source_sets": {
        "app": {
            "main_assets_directory": [
                "E:\\MyWorkSpace\\DoingDaily\\app\\src\\debug\\assets",
                "E:\\MyWorkSpace\\DoingDaily\\app\\src\\main\\assets"
            ],
            "main_jniLibs_directory": [
                "E:\\MyWorkSpace\\DoingDaily\\app\\src\\debug\\jniLibs",
                "E:\\MyWorkSpace\\DoingDaily\\app\\src\\main\\jniLibs"
            ],
            "main_jni_directory": [
                "E:\\MyWorkSpace\\DoingDaily\\app\\src\\debug\\jni",
                "E:\\MyWorkSpace\\DoingDaily\\app\\src\\main\\jni"
            ],
            "main_manifest_path": "E:\\MyWorkSpace\\DoingDaily\\app\\src\\main\\AndroidManifest.xml",
            "main_res_directory": [
                "E:\\MyWorkSpace\\DoingDaily\\app\\src\\debug\\res",
                "E:\\MyWorkSpace\\DoingDaily\\app\\src\\main\\res"
            ],
            "main_src_directory": [
                "E:\\MyWorkSpace\\DoingDaily\\app\\src\\debug\\java",
                "E:\\MyWorkSpace\\DoingDaily\\app\\src\\main\\java"
            ]
        }
    },
    "project_type": "gradle",
    "root_dir": "E:\\MyWorkSpace\\DoingDaily",
    "sdk_directory": "D:\\AndroidDevTools\\sdk",
    "use_jdk8": false
}